<!DOCTYPE componentassembly SYSTEM "componentassembly.dtd">
<componentassembly id="ZZZ123">
  <description>Example assembly"</description>

  <componentfiles>
    <componentfile id="A"> <fileinarchive name="ca.ccsd"/> </componentfile>
    <componentfile id="B"> <fileinarchive name="cb.ccsd"/> </componentfile>
    <componentfile id="C">
      <fileinarchive name="cc.ccsd">
        <link href="ftp://www.xyz.com/car/cc.car"/>
      </fileinarchive>
    </componentfile>
    <componentfile id="D"> <fileinarchive name="cd.ccsd"/> </componentfile>
    <componentfile id="E"> <fileinarchive name="ce.ccsd"/> </componentfile>
    <componentfile id="F"> <fileinarchive name="cf.ccsd"/> </componentfile>
  </componentfiles>

  <partitioning>
    <homeplacement id="AaHome">
      <componentfileref idref="A"/> <componentinstantiation id="Aa"/>
    </homeplacement>

    <processcollocation cardinality="*">
      <usagename>Example process collocation</usagename>
      <impltype language="C++" />
      <!-- optional -->
      <homeplacement id="BbHome">
        <componentfileref idref="B"/> <componentinstantiation id="Bb"/>
      </homeplacement>
      <homeplacement id="CcHome">
        <componentfileref idref="C"/>
        <componentinstantiation id="Cc"/>
      </homeplacement>
    </processcollocation>

    <hostcollocation cardinality="1">
      <usagename>Example host collocation</usagename>

      <processcollocation cardinality="*">

        <homeplacement id="DdHome">
          <componentfileref idref="D"/>
          <componentinstantiation id="Dd"/>
        </homeplacement>

        <homeplacement id="EdHome">
          <componentfileref idref="E"/>
          <componentinstantiation id="Ee"/>
        </homeplacement>

      </processcollocation>

      <homeplacement id="FfHome">
        <componentfileref idref="F"/>
        <componentinstantiation id="Ff"/>
      </homeplacement>

    </hostcollocation>

    <homeplacement id="AaaHome">

      <usagename>Example home for A components</usagename>
      <componentfileref idref="A"/>
      <componentimplref idref="an A impl"/>

      <homeproperties>
        <fileinarchive name="AHomeProperties.cpf"/>
      </homeproperties>

      <componentproperties>
        <fileinarchive name="defaultAProperties.cpf"/>
      </componentproperties>

      <registerwithhomefinder name="AaHome"/>

      <componentinstantiation id="Aaa">
        <usagename>Example component instantiation </usagename>

        <componentproperties>
          <fileinarchive name="AaaProperties.cpf"/>
        </componentproperties>

        <registercomponent>
          <registerwithnaming name="sink"/>

          <registerwithtrader>

            <traderproperties>

              <traderproperty>
                <traderpropertyname>ppm</traderpropertyname>
                <traderpropertyvalue>10</traderpropertyvalue>
              </traderproperty>

              <traderproperty>
                <traderpropertyname>weight</traderpropertyname>
                <traderpropertyvalue>333</traderpropertyvalue>
              </traderproperty>

            </traderproperties>

          </registerwithtrader>

        </registercomponent>

      </componentinstantiation>

    </homeplacement>

  </partitioning>

  <connections>

    <connectinterface>
      <usesport>
        <usesidentifier>abc</usesidentifier>
        <componentinstantiationref idref="Aa"/>
      </usesport>
      <providesport>
        <providesidentifier>abc</providesidentifier>
        <componentinstantiationref idref="Bb"/>
      </providesport>
    </connectinterface>

    <connectevent>
      <consumesport>
        <consumesidentifier>pqr</consumesidentifier>
        <componentinstantiationref idref="Aaa"/>
      </consumesport>
      <emitsport>
        <emitsidentifier>mno</emitsidentifier>
        <componentinstantiationref idref="Ee"/>
      </emitsport>
    </connectevent>

  </connections>

</componentassembly>
